Workbook

Sheet INDEX
B9: Netflix Valuation Using DCF Method
C11: S.No | D11: Sheet Name
C12: 1 | D12: Revenue Modelling
C13: 2 | D13: Other Items
C14: 3 | D14: Schedules
C15: 4 | D15: P&L
C16: 5 | D16: Balance Sheet
C17: 6 | D17: Cash Flow Statement
C18: 7 | D18: WACC
C19: 8 | D19: DCF

Sheet P&L Input
C3: P&L Statement
D5: (in thousands)
C6: Description | D6: 2024 ($) | E6: 2023 ($) | F6: 2022 ($)
C7: Revenues | D7: 39000966 | E7: 33723297 | F7: 31615550
C8: Cost of revenues | D8: 21038464 | E8: 19715368 | F8: 19168285
C9: Sales and marketing | D9: 2917554 | E9: 2657883 | F9: 2530502
C10: Technology and development | D10: 2925295 | E10: 2675758 | F10: 2711041
C11: General and administrative | D11: 1702039 | E11: 1720285 | F11: 1572891
C12: Operating income | D12: 10417614 | E12: 6954003 | F12: 5632831
C13: Other income (expense):
C14: Interest expense | D14: -718733 | E14: -699826 | F14: -706212
C15: Interest and other income (expense) | D15: 266776 | E15: -48772 | F15: 337310
C16: Income before income taxes | D16: 9965657 | E16: 6205405 | F16: 5263929
C17: Provision for income taxes | D17: -1254026 | E17: -797415 | F17: -772005
C18: Net income | D18: 8711631 | E18: 5407990 | F18: 4491924

Sheet Balance Sheet Input
C3: Balance Sheet
D5: (in thousands)
C6: Description | D6: 2024 ($) | E6: 2023 ($) | F6: 2022 ($)
C7: Assets
C8: Current assets:
C9: Cash and cash equivalents | D9: 7804733 | E9: 7116913 | F9: 5147176
C10: Short-term investments | D10: 1779006 | E10: 20973 | F10: 911276
C11: Other current assets | D11: 3516640 | E11: 2780247 | F11: 3208021
C12: Total current assets | D12: 13100379 | E12: 9918133 | F12: 9266473
C13: Content assets, net | D13: 32452462 | E13: 31658056 | F13: 32736713
C14: Property and equipment, net | D14: 1593756 | E14: 1491444 | F14: 1398257
C15: Other non-current assets | D15: 6483777 | E15: 5664359 | F15: 5193325
C16: Total assets | D16: 53630374 | E16: 48731992 | F16: 48594768
C17: Liabilities and Stockholders' Equity
C18: Current liabilities:
C19: Current content liabilities | D19: 4393681 | E19: 4466470 | F19: 4480150
C20: Accounts payable | D20: 899909 | E20: 747412 | F20: 671513
C21: Accrued expenses and other liabilities | D21: 2156544 | E21: 1803960 | F21: 1514650
C22: Deferred revenue | D22: 1520813 | E22: 1442969 | F22: 1264661
C23: Short-term debt | D23: 1784453 | E23: 399844 | F23: -
C24: Total current liabilities | D24: 10755400 | E24: 8860655 | F24: 7930974
C25: Non-current content liabilities | D25: 1780806 | E25: 2578173 | F25: 3081277
C26: Long-term debt | D26: 13798351 | E26: 14143417 | F26: 14353076
C27: Other non-current liabilities | D27: 2552250 | E27: 2561434 | F27: 2452040
C28: Total liabilities | D28: 28886807 | E28: 28143679 | F28: 27817367
C29: Stockholders' equity:
C30: Common stock | D30: 6252126 | E30: 5145172 | F30: 4637601
C31: Treasury stock | D31: -13171638 | E31: -6922200 | F31: -824190
C32: Accumulated other comprehensive income (loss) | D32: 362162 | E32: -223945 | F32: -217306
C33: Retained earnings | D33: 31300917 | E33: 22589286 | F33: 17181296
C34: Total stockholders' equity | D34: 24743567 | E34: 20588313 | F34: 20777401
C35: Total liabilities and stockholders' equity | D35: 53630374 | E35: 48731992 | F35: 48594768

Sheet Revenue Modelling
A1: Revenue Sources
A2: (in thousands) | B2: 2022 Act | C2: 2023 Act | D2: 2024 Act | E2: 2025 Forcasted | F2: 2026 Forcasted | G2: 2027 Forcasted | H2: 2028 Forcasted
A3: Streaming revenues | B3: =B10+B17+B24+B31 -> 31469852 | C3: =C10+C17+C24+C31 -> 33640458 | D3: =D10+D17+D24+D31 -> 39000966 | E3: =D3*(1+E5) -> 43453340 | F3: =E3*(1+F5) -> 48413999 | G3: =F3*(1+G5) -> 53940970 | H3: =G3*(1+H5) -> 60098904
A4: DVD Revenues | B4: ='P&L Input'!F7-'Revenue Modelling'!B3 -> 145698 | C4: ='P&L Input'!E7-'Revenue Modelling'!C3 -> 82839 | D4: ='P&L Input'!D7-'Revenue Modelling'!D3 -> 0 | E4: 0 | F4: 0 | G4: 0 | H4: 0
A5: Growth % | C5: =C3/B3-1 -> 0.068974141 | D5: =D3/C3-1 -> 0.15934706 | E5: =AVERAGE($C$5:$D$5) -> 0.1141606 | F5: =AVERAGE($C$5:$D$5) -> 0.1141606 | G5: =AVERAGE($C$5:$D$5) -> 0.1141606 | H5: =AVERAGE($C$5:$D$5) -> 0.1141606
A6: Total Revenues | B6: =SUM(B3:B4) -> 31615550 | C6: =SUM(C3:C4) -> 33723297 | D6: =SUM(D3:D4) -> 39000966 | E6: =SUM(E3:E4) -> 43453340 | F6: =SUM(F3:F4) -> 48413999 | G6: =SUM(G3:G4) -> 53940970 | H6: =SUM(H3:H4) -> 60098904
A9: Unites States and Canada ( in thousands)
A10: Revenues | B10: 14084643 | C10: 14873783 | D10: 17359369 | E10: =E12*E11 -> 25654823 | F10: =F12*F11 -> 31073239 | G10: =G12*G11 -> 37325317 | H10: =H12*H11 -> 44462089 | I10: Average Monthly Revenues
A11: Average yearly revenue per membership | B11: =I12*12 -> 191.76 | C11: =J12*12 -> 181.44 | D11: =K12*12 -> 156.72 | E11: =AVERAGE($B$11:$D$11) -> 176.64 | F11: =AVERAGE($B$11:$D$11) -> 176.64 | G11: =AVERAGE($B$11:$D$11) -> 176.64 | H11: =AVERAGE($B$11:$D$11) -> 176.64 | I11: 2022 | J11: 2023 | K11: 2024
A12: Average Paid membership | B12: =B10/B11 -> 73449.327 | C12: =C10/C11 -> 81976.317 | D12: =D10/D11 -> 110766.78 | E12: =D12*(1+E13) -> 145237.9 | F12: =E12*(1+F13) -> 175912.81 | G12: =F12*(1+G13) -> 211307.28 | H12: =G12*(1+H13) -> 251710.19 | I12: 15.98 | J12: 15.12 | K12: 13.06
A13: Growth % | C13: =C12/B12-1 -> 0.11609351 | D13: =D12/C12-1 -> 0.35120458 | E13: =D13-4% -> 0.31120458 | F13: =E13-10% -> 0.21120458 | G13: =F13-1% -> 0.20120458 | H13: =G13-1% -> 0.19120458 | I13: Industry Average - 19 to 21%
A16: Europe, Middle East, and Africa (EMEA) (in thousands)
A17: Revenues | B17: 9745015 | C17: 10556487 | D17: 12387035 | E17: =E19*E18 -> 13886084 | F17: =F19*F18 -> 15255693 | G17: =G19*G18 -> 16607832 | H17: =H19*H18 -> 17913736 | I17: Average Monthly Revenues
A18: Average yearly revenue per membership | B18: =I19*12 -> 130.68 | C18: =J19*12 -> 127.56 | D18: =K19*12 -> 130.44 | E18: =AVERAGE($B$18:$D$18) -> 129.56 | F18: =AVERAGE($B$18:$D$18) -> 129.56 | G18: =AVERAGE($B$18:$D$18) -> 129.56 | H18: =AVERAGE($B$18:$D$18) -> 129.56 | I18: 2022 | J18: 2023 | K18: 2024
A19: Average Paid membership | B19: =B17/B18 -> 74571.587 | C19: =C17/C18 -> 82757.032 | D19: =D17/D18 -> 94963.47 | E19: =D19*(1+E20) -> 107178.79 | F19: =E19*(1+F20) -> 117750.02 | G19: =F19*(1+G20) -> 128186.42 | H19: =G19*(1+H20) -> 138265.94 | I19: 10.89 | J19: 10.63 | K19: 10.87
A20: Growth % | C20: =C19/B19-1 -> 0.10976627 | D20: =D19/C19-1 -> 0.14749729 | E20: =AVERAGE(C20:D20) -> 0.12863178 | F20: =E20-3% -> 0.098631779 | G20: =F20-1% -> 0.088631779 | H20: =G20-1% -> 0.078631779 | I20: Industry Average - 7 to 9%
A23: Latin America (LATAM) (in thousands)
A24: Revenues | B24: 4069973 | C24: 4446461 | D24: 4839816 | E24: =E26*E25 -> 5449612 | F24: =F26*F25 -> 5955909.9 | G24: =G26*G25 -> 6449686.4 | H24: =H26*H25 -> 6952151.2 | I24: Average Monthly Revenues
A25: Average yearly revenue per membership | B25: =I26*12 -> 99.6 | C25: =J26*12 -> 101.4 | D25: =K26*12 -> 97.44 | E25: =AVERAGE($B$25:$D$25) -> 99.48 | F25: =AVERAGE($B$25:$D$25) -> 99.48 | G25: =AVERAGE($B$25:$D$25) -> 99.48 | H25: =AVERAGE($B$25:$D$25) -> 99.48 | I25: 2022 | J25: 2023 | K25: 2024
A26: Average Paid membership | B26: =B24/B25 -> 40863.183 | C26: =C24/C25 -> 43850.7 | D26: =D24/D25 -> 49669.704 | E26: =D26*(1+E27) -> 54780.981 | F26: =E26*(1+F27) -> 59870.425 | G26: =F26*(1+G27) -> 64834.001 | H26: =G26*(1+H27) -> 69884.914 | I26: 8.3 | J26: 8.45 | K26: 8.12
A27: Growth % | C27: =C26/B26-1 -> 0.073110249 | D27: =D26/C26-1 -> 0.13270037 | E27: =AVERAGE(C27:D27) -> 0.10290531 | F27: =E27-1% -> 0.092905311 | G27: =F27-1% -> 0.082905311 | H27: =G27-0.5% -> 0.077905311 | I27: Industry Average - 7.6%
A30: Asia-Pacific (in thousands)
A31: Revenues | B31: 3570221 | C31: 3763727 | D31: 4414746 | E31: =E33*E32 -> 5733450.8 | F31: =F33*F32 -> 6991987.8 | G31: =G33*G32 -> 8483003.9 | H31: =H33*H32 -> 10318531 | I31: Average Monthly Revenues
A32: Average yearly revenue per membership | B32: =I33*12 -> 101.04 | C32: =J33*12 -> 90.12 | D32: =K33*12 -> 85.8 | E32: =AVERAGE($B$32:$D$32) -> 92.32 | F32: =AVERAGE($B$32:$D$32) -> 92.32 | G32: =AVERAGE($B$32:$D$32) -> 92.32 | H32: =AVERAGE($B$32:$D$32) -> 92.32 | I32: 2022 | J32: 2023 | K32: 2024
A33: Average Paid membership | B33: =B31/B32 -> 35334.729 | C33: =C31/C32 -> 41763.504 | D33: =D31/D32 -> 51453.916 | E33: =D33*(1+E34) -> 62104.103 | F33: =E33*(1+F34) -> 75736.437 | G33: =F33*(1+G34) -> 91886.957 | H33: =G33*(1+H34) -> 111769.19 | I33: 8.42 | J33: 7.51 | K33: 7.15
A34: Growth % | C34: =C33/B33-1 -> 0.18193929 | D34: =D33/C33-1 -> 0.23203062 | E34: =AVERAGE(C34:D34) -> 0.20698495 | F34: =AVERAGE(D34:E34) -> 0.21950779 | G34: =AVERAGE(E34:F34) -> 0.21324637 | H34: =AVERAGE(F34:G34) -> 0.21637708 | I34: Industry Average - 22.5%

Sheet Other Items
A1: Other Items
A3: (in thousands) | B3: 2022 | C3: 2023 | D3: 2024 | E3: 2025 | F3: 2026 | G3: 2027 | H3: 2028
A4: Cost of Goods Sold | B4: ='P&L Input'!F8-Schedules!B6 -> 18831603 | C4: ='P&L Input'!E8-Schedules!C6 -> 19358421 | D4: ='P&L Input'!D8-Schedules!D6 -> 20709550 | E4: ='Revenue Modelling'!E6*'Other Items'!E5 -> 24633433 | F4: ='Revenue Modelling'!F6*'Other Items'!F5 -> 27445600 | G4: ='Revenue Modelling'!G6*'Other Items'!G5 -> 30578806 | H4: ='Revenue Modelling'!H6*'Other Items'!H5 -> 34069701
A5: as a % revenues | B5: =B4/'Revenue Modelling'!B6 -> 0.59564369 | C5: =C4/'Revenue Modelling'!C6 -> 0.57403702 | D5: =D4/'Revenue Modelling'!D6 -> 0.53100095 | E5: =AVERAGE($B$5:$D$5) -> 0.56689389 | F5: =AVERAGE($B$5:$D$5) -> 0.56689389 | G5: =AVERAGE($B$5:$D$5) -> 0.56689389 | H5: =AVERAGE($B$5:$D$5) -> 0.56689389
A7: Sales and Marketing | B7: ='P&L Input'!F9 -> 2530502 | C7: ='P&L Input'!E9 -> 2657883 | D7: ='P&L Input'!D9 -> 2917554 | E7: ='Revenue Modelling'!E6*'Other Items'!E8 -> 3384456.9 | F7: ='Revenue Modelling'!F6*'Other Items'!F8 -> 3770828.6 | G7: ='Revenue Modelling'!G6*'Other Items'!G8 -> 4201308.6 | H7: ='Revenue Modelling'!H6*'Other Items'!H8 -> 4680932.5
A8: as a % revenues | B8: =B7/'Revenue Modelling'!B6 -> 0.080039791 | C8: =C7/'Revenue Modelling'!C6 -> 0.078814447 | D8: =D7/'Revenue Modelling'!D6 -> 0.074807224 | E8: =AVERAGE($B$8:$D$8) -> 0.077887154 | F8: =AVERAGE($B$8:$D$8) -> 0.077887154 | G8: =AVERAGE($B$8:$D$8) -> 0.077887154 | H8: =AVERAGE($B$8:$D$8) -> 0.077887154
A10: Technology and Development | B10: ='P&L Input'!F10 -> 2711041 | C10: ='P&L Input'!E10 -> 2675758 | D10: ='P&L Input'!D10 -> 2925295 | E10: ='Revenue Modelling'!E6*'Other Items'!E11 -> 3477722 | F10: ='Revenue Modelling'!F6*'Other Items'!F11 -> 3874740.9 | G10: ='Revenue Modelling'!G6*'Other Items'!G11 -> 4317083.6 | H10: ='Revenue Modelling'!H6*'Other Items'!H11 -> 4809924.4
A11: as a % revenues | B11: =B10/'Revenue Modelling'!B6 -> 0.08575024 | C11: =C10/'Revenue Modelling'!C6 -> 0.079344496 | D11: =D10/'Revenue Modelling'!D6 -> 0.075005706 | E11: =AVERAGE($B$11:$D$11) -> 0.080033481 | F11: =AVERAGE($B$11:$D$11) -> 0.080033481 | G11: =AVERAGE($B$11:$D$11) -> 0.080033481 | H11: =AVERAGE($B$11:$D$11) -> 0.080033481
A13: General and Administrative | B13: ='P&L Input'!F11 -> 1572891 | C13: ='P&L Input'!E11 -> 1720285 | D13: ='P&L Input'!D11 -> 1702039 | E13: ='Revenue Modelling'!E6*'Other Items'!E14 -> 2091601.3 | F13: ='Revenue Modelling'!F6*'Other Items'!F14 -> 2330379.8 | G13: ='Revenue Modelling'!G6*'Other Items'!G14 -> 2596417.4 | H13: ='Revenue Modelling'!H6*'Other Items'!H14 -> 2892825.9
A14: as a % revenues | B14: =B13/'Revenue Modelling'!B6 -> 0.04975055 | C14: =C13/'Revenue Modelling'!C6 -> 0.051011768 | D14: =D13/'Revenue Modelling'!D6 -> 0.043640945 | E14: =AVERAGE($B$14:$D$14) -> 0.048134421 | F14: =AVERAGE($B$14:$D$14) -> 0.048134421 | G14: =AVERAGE($B$14:$D$14) -> 0.048134421 | H14: =AVERAGE($B$14:$D$14) -> 0.048134421
A16: Other Current assets | B16: ='Balance Sheet Input'!F11 -> 3208021 | C16: ='Balance Sheet Input'!E11 -> 2780247 | D16: ='Balance Sheet Input'!D11 -> 3516640 | E16: ='Revenue Modelling'!E6*'Other Items'!E17 -> 3969906.7 | F16: ='Revenue Modelling'!F6*'Other Items'!F17 -> 4423113.6 | G16: ='Revenue Modelling'!G6*'Other Items'!G17 -> 4928058.9 | H16: ='Revenue Modelling'!H6*'Other Items'!H17 -> 5490649.1
A17: as a % revenues | B17: =B16/'Revenue Modelling'!B6 -> 0.10146972 | C17: =C16/'Revenue Modelling'!C6 -> 0.082442918 | D17: =D16/'Revenue Modelling'!D6 -> 0.090168023 | E17: =AVERAGE($B$17:$D$17) -> 0.09136022 | F17: =AVERAGE($B$17:$D$17) -> 0.09136022 | G17: =AVERAGE($B$17:$D$17) -> 0.09136022 | H17: =AVERAGE($B$17:$D$17) -> 0.09136022
A19: Accounts Payable | B19: ='Balance Sheet Input'!F20 -> 671513 | C19: ='Balance Sheet Input'!E20 -> 747412 | D19: ='Balance Sheet Input'!D20 -> 899909 | E19: =(E20*E4)/365 -> 966630.61 | F19: =(F20*F4)/365 -> 1076981.7 | G19: =(G20*G4)/365 -> 1199930.6 | H19: =(H20*H4)/365 -> 1336915.4
A20: Days Payable | B20: =B19/B4*365 -> 13.015474 | C20: =C19/C4*365 -> 14.092336 | D20: =D19/D4*365 -> 15.860643 | E20: =AVERAGE($B$20:$D$20) -> 14.322818 | F20: =AVERAGE($B$20:$D$20) -> 14.322818 | G20: =AVERAGE($B$20:$D$20) -> 14.322818 | H20: =AVERAGE($B$20:$D$20) -> 14.322818
A22: Accrued Expenses and other Liabilities | B22: ='Balance Sheet Input'!F21 -> 1514650 | C22: ='Balance Sheet Input'!E21 -> 1803960 | D22: ='Balance Sheet Input'!D21 -> 2156544 | E22: ='Revenue Modelling'!E6*'Other Items'!E23 -> 2269654.9 | F22: ='Revenue Modelling'!F6*'Other Items'!F23 -> 2528760.1 | G22: ='Revenue Modelling'!G6*'Other Items'!G23 -> 2817444.9 | H22: ='Revenue Modelling'!H6*'Other Items'!H23 -> 3139086.1
A23: as a % revenues | B23: =B22/'Revenue Modelling'!B6 -> 0.047908387 | C23: =C22/'Revenue Modelling'!C6 -> 0.05349299 | D23: =D22/'Revenue Modelling'!D6 -> 0.05529463 | E23: =AVERAGE($B$23:$D$23) -> 0.052232003 | F23: =AVERAGE($B$23:$D$23) -> 0.052232003 | G23: =AVERAGE($B$23:$D$23) -> 0.052232003 | H23: =AVERAGE($B$23:$D$23) -> 0.052232003
A25: Deferred Revenue | B25: ='Balance Sheet Input'!F22 -> 1264661 | C25: ='Balance Sheet Input'!E22 -> 1442969 | D25: ='Balance Sheet Input'!D22 -> 1520813 | E25: ='Revenue Modelling'!E6*'Other Items'!E26 -> 1763973.3 | F25: ='Revenue Modelling'!F6*'Other Items'!F26 -> 1965349.6 | G25: ='Revenue Modelling'!G6*'Other Items'!G26 -> 2189715.1 | H25: ='Revenue Modelling'!H6*'Other Items'!H26 -> 2439694.2
A26: as a % revenues | B26: =B25/'Revenue Modelling'!B6 -> 0.040001234 | C26: =C25/'Revenue Modelling'!C6 -> 0.042788491 | D26: =D25/'Revenue Modelling'!D6 -> 0.038994239 | E26: =AVERAGE($B$26:$D$26) -> 0.040594655 | F26: =AVERAGE($B$26:$D$26) -> 0.040594655 | G26: =AVERAGE($B$26:$D$26) -> 0.040594655 | H26: =AVERAGE($B$26:$D$26) -> 0.040594655

Sheet Schedules
A2: PP&E
A3: (in thousands) | B3: 2022 | C3: 2023 | D3: 2024 | E3: 2025 | F3: 2026 | G3: 2027 | H3: 2028
A4: Beginning Balance | C4: =B7 -> 1398257 | D4: =C7 -> 1491444 | E4: =D7 -> 1593756 | F4: =E7 -> 1688154.3 | G4: =F7 -> 1793918.7 | H4: =G7 -> 1907807.4
A5: add: Capex | C5: =C7+C6-C4 -> 450134 | D5: =D7+D6-D4 -> 431226 | E5: =$D$5 -> 431226 | F5: =$D$5 -> 431226 | G5: =$D$5 -> 431226 | H5: =$D$5 -> 431226
A6: less: Depreciation | B6: 336682 | C6: 356947 | D6: 328914 | E6: =(E4+E5)/E9 -> 336827.71 | F6: =(F4+F5)/F9 -> 325461.55 | G6: =(G4+G5)/G9 -> 317337.34 | H6: =(H4+H5)/H9 -> 311376.15
A7: Closing Balance | B7: ='Balance Sheet Input'!F14 -> 1398257 | C7: ='Balance Sheet Input'!E14 -> 1491444 | D7: ='Balance Sheet Input'!D14 -> 1593756 | E7: =E4+E5-E6 -> 1688154.3 | F7: =F4+F5-F6 -> 1793918.7 | G7: =G4+G5-G6 -> 1907807.4 | H7: =H4+H5-H6 -> 2027657.2
A9: Useful life | C9: =(C4+C5)/C6 -> 5.1783346 | D9: =(D4+D5)/D6 -> 5.8455098 | E9: =AVERAGE(C9:D9)+0.5 -> 6.0119222 | F9: =E9+0.5 -> 6.5119222 | G9: =F9+0.5 -> 7.0119222 | H9: =G9+0.5 -> 7.5119222
A12: Content Assets
A13: (in thousands) | B13: 2022 | C13: 2023 | D13: 2024 | E13: 2025 | F13: 2026 | G13: 2027 | H13: 2028
A14: Beginning Balance | C14: =B17 -> 32736713 | D14: =C17 -> 31658056 | E14: =D17 -> 32452462 | F14: =E17 -> 33259261 | G14: =F17 -> 33811979 | H14: =G17 -> 34190632
A15: add: Addition to Content Assets | C15: =C17+C16-C14 -> 13118780 | D15: =D17+D16-D14 -> 16095923 | E15: =$D$15 -> 16095923 | F15: =$D$15 -> 16095923 | G15: =$D$15 -> 16095923 | H15: =$D$15 -> 16095923
A16: less: Amortisation of Content Assets | B16: 14026132 | C16: 14197437 | D16: 15301517 | E16: =(E14+E15)/E19 -> 15289124 | F16: =(F14+F15)/F19 -> 15543205 | G16: =(G14+G15)/G19 -> 15717270 | H16: =(H14+H15)/H19 -> 15836518
A17: Closing Balance | B17: ='Balance Sheet Input'!F13 -> 32736713 | C17: ='Balance Sheet Input'!E13 -> 31658056 | D17: ='Balance Sheet Input'!D13 -> 32452462 | E17: =E14+E15-E16 -> 33259261 | F17: =F14+F15-F16 -> 33811979 | G17: =G14+G15-G16 -> 34190632 | H17: =H14+H15-H16 -> 34450037
A19: Useful life | C19: =(C14+C15)/C16 -> 3.229843 | D19: =(D14+D15)/D16 -> 3.1208657 | E19: =AVERAGE($C$19:$D$19) -> 3.1753543 | F19: =AVERAGE($C$19:$D$19) -> 3.1753543 | G19: =AVERAGE($C$19:$D$19) -> 3.1753543 | H19: =AVERAGE($C$19:$D$19) -> 3.1753543
A22: Debt Schedule
A23: Beginning Balance of Debt | C23: =B25 -> 14353076 | D23: =C25 -> 14143417 | E23: =D25 -> 13798351 | F23: =E25 -> 12011351 | G23: =F25 -> 11011351 | H23: =G25 -> 9577351
A24: add/less: Debt Taken /(debt repaid) | C24: =C23-C25 -> 209659 | D24: =D23-D25 -> 345066 | E24: =-(800000+487000+500000) -> -1787000 | F24: =-1000000 -> -1000000 | G24: =-1434000 -> -1434000 | H24: =-(1600000+1900000) -> -3500000
A25: Closing Balance | B25: ='Balance Sheet Input'!F26 -> 14353076 | C25: ='Balance Sheet Input'!E26 -> 14143417 | D25: ='Balance Sheet Input'!D26 -> 13798351 | E25: =E23+E24 -> 12011351 | F25: =F23+F24 -> 11011351 | G25: =G23+G24 -> 9577351 | H25: =H23+H24 -> 6077351
A27: Interest Expense | B27: ='P&L Input'!F14 -> -706212 | C27: ='P&L Input'!E14 -> -699826 | D27: ='P&L Input'!D14 -> -718733 | E27: =E25*E28 -> -603657.86 | F27: =F25*F28 -> -553400.57 | G27: =G25*G28 -> -481331.63 | H27: =H25*H28 -> -305431.14
B28: =B27/B25 -> -0.049202833 | C28: =C27/C25 -> -0.049480688 | D28: =D27/D25 -> -0.052088326 | E28: =AVERAGE($B$28:$D$28) -> -0.050257282 | F28: =AVERAGE($B$28:$D$28) -> -0.050257282 | G28: =AVERAGE($B$28:$D$28) -> -0.050257282 | H28: =AVERAGE($B$28:$D$28) -> -0.050257282

Sheet P&L
A1: P&L Forcasting
A3: (in thousands) | B3: 2022 | C3: 2023 | D3: 2024 | E3: 2025 | F3: 2026 | G3: 2027 | H3: 2028
A4: Streaming revenues | B4: ='Revenue Modelling'!B3 -> 31469852 | C4: ='Revenue Modelling'!C3 -> 33640458 | D4: ='Revenue Modelling'!D3 -> 39000966 | E4: ='Revenue Modelling'!E3 -> 43453340 | F4: ='Revenue Modelling'!F3 -> 48413999 | G4: ='Revenue Modelling'!G3 -> 53940970 | H4: ='Revenue Modelling'!H3 -> 60098904
A5: DVD Revenues | B5: ='Revenue Modelling'!B4 -> 145698 | C5: ='Revenue Modelling'!C4 -> 82839 | D5: ='Revenue Modelling'!D4 -> 0 | E5: ='Revenue Modelling'!E4 -> 0 | F5: ='Revenue Modelling'!F4 -> 0 | G5: ='Revenue Modelling'!G4 -> 0 | H5: ='Revenue Modelling'!H4 -> 0
A6: Total Revenues | B6: =SUM(B4:B5) -> 31615550 | C6: =SUM(C4:C5) -> 33723297 | D6: =SUM(D4:D5) -> 39000966 | E6: =SUM(E4:E5) -> 43453340 | F6: =SUM(F4:F5) -> 48413999 | G6: =SUM(G4:G5) -> 53940970 | H6: =SUM(H4:H5) -> 60098904
A7: Cost of Goods Sold | B7: ='Other Items'!B4 -> 18831603 | C7: ='Other Items'!C4 -> 19358421 | D7: ='Other Items'!D4 -> 20709550 | E7: ='Other Items'!E4 -> 24633433 | F7: ='Other Items'!F4 -> 27445600 | G7: ='Other Items'!G4 -> 30578806 | H7: ='Other Items'!H4 -> 34069701
A8: Gross Margin | B8: =B6-B7 -> 12783947 | C8: =C6-C7 -> 14364876 | D8: =D6-D7 -> 18291416 | E8: =E6-E7 -> 18819907 | F8: =F6-F7 -> 20968399 | G8: =G6-G7 -> 23362164 | H8: =H6-H7 -> 26029202
A9: Operating Expenses:
A10: Marketing | B10: ='Other Items'!B7 -> 2530502 | C10: ='Other Items'!C7 -> 2657883 | D10: ='Other Items'!D7 -> 2917554 | E10: ='Other Items'!E7 -> 3384456.9 | F10: ='Other Items'!F7 -> 3770828.6 | G10: ='Other Items'!G7 -> 4201308.6 | H10: ='Other Items'!H7 -> 4680932.5
A11: Technology and development | B11: ='Other Items'!B10 -> 2711041 | C11: ='Other Items'!C10 -> 2675758 | D11: ='Other Items'!D10 -> 2925295 | E11: ='Other Items'!E10 -> 3477722 | F11: ='Other Items'!F10 -> 3874740.9 | G11: ='Other Items'!G10 -> 4317083.6 | H11: ='Other Items'!H10 -> 4809924.4
A12: General and administrative | B12: ='Other Items'!B13 -> 1572891 | C12: ='Other Items'!C13 -> 1720285 | D12: ='Other Items'!D13 -> 1702039 | E12: ='Other Items'!E13 -> 2091601.3 | F12: ='Other Items'!F13 -> 2330379.8 | G12: ='Other Items'!G13 -> 2596417.4 | H12: ='Other Items'!H13 -> 2892825.9
A13: EBITDA | B13: =B8-SUM(B10:B12) -> 5969513 | C13: =C8-SUM(C10:C12) -> 7310950 | D13: =D8-SUM(D10:D12) -> 10746528 | E13: =E8-SUM(E10:E12) -> 9866126.6 | F13: =F8-SUM(F10:F12) -> 10992450 | G13: =G8-SUM(G10:G12) -> 12247354 | H13: =H8-SUM(H10:H12) -> 13645519
A14: less: Depreciation | B14: =Schedules!B6 -> 336682 | C14: =Schedules!C6 -> 356947 | D14: =Schedules!D6 -> 328914 | E14: =Schedules!E6 -> 336827.71 | F14: =Schedules!F6 -> 325461.55 | G14: =Schedules!G6 -> 317337.34 | H14: =Schedules!H6 -> 311376.15
A15: EBIT | B15: =B13-B14 -> 5632831 | C15: =C13-C14 -> 6954003 | D15: =D13-D14 -> 10417614 | E15: =E13-E14 -> 9529298.9 | F15: =F13-F14 -> 10666988 | G15: =G13-G14 -> 11930017 | H15: =H13-H14 -> 13334143
A16: Interest | B16: =Schedules!B27 -> -706212 | C16: =Schedules!C27 -> -699826 | D16: =Schedules!D27 -> -718733 | E16: =Schedules!E27 -> -603657.86 | F16: =Schedules!F27 -> -553400.57 | G16: =Schedules!G27 -> -481331.63 | H16: =Schedules!H27 -> -305431.14
A17: Interest and other income (expense) | B17: ='P&L Input'!F15 -> 337310 | C17: ='P&L Input'!E15 -> -48772 | D17: ='P&L Input'!D15 -> 266776 | E17: 0 | F17: 0 | G17: 0 | H17: 0
A18: EBT | B18: =B15+B16+B17 -> 5263929 | C18: =C15+C16+C17 -> 6205405 | D18: =D15+D16+D17 -> 9965657 | E18: =E15+E16+E17 -> 8925641.1 | F18: =F15+F16+F17 -> 10113587 | G18: =G15+G16+G17 -> 11448685 | H18: =H15+H16+H17 -> 13028712
A19: Taxes | B19: ='P&L Input'!F17 -> -772005 | C19: ='P&L Input'!E17 -> -797415 | D19: ='P&L Input'!D17 -> -1254026 | E19: =E18*E20 -> -1284832.4 | F19: =F18*F20 -> -1455835.5 | G19: =G18*G20 -> -1648020.8 | H19: =H18*H20 -> -1875463.3
A20: tax rate % | B20: =B19/B21 -> -0.17186511 | C20: =C19/C21 -> -0.14745127 | D20: =D19/D21 -> -0.14394848 | E20: =$D$20 -> -0.14394848 | F20: =$D$20 -> -0.14394848 | G20: =$D$20 -> -0.14394848 | H20: =$D$20 -> -0.14394848
A21: Net Income | B21: =B18+B19 -> 4491924 | C21: =C18+C19 -> 5407990 | D21: =D18+D19 -> 8711631 | E21: =E18+E19 -> 7640808.6 | F21: =F18+F19 -> 8657752 | G21: =G18+G19 -> 9800664.4 | H21: =H18+H19 -> 11153249

Sheet Balance Sheet
A1: Balance Sheet
A3: (in thousands) | B3: 2022 | C3: 2023 | D3: 2024 | E3: 2025 | F3: 2026 | G3: 2027 | H3: 2028
A4: Assets
A5: Current assets:
A6: Cash and cash equivalents | B6: 5147176 | C6: 7116913 | D6: 7804733 | E6: =D6+'Cashflow Statement'!E25 -> 12727070 | F6: =E6+'Cashflow Statement'!F25 -> 19843966 | G6: =F6+'Cashflow Statement'!G25 -> 27849142 | H6: =G6+'Cashflow Statement'!H25 -> 35269151
A7: Short term Investments | B7: 911276 | C7: 20973 | D7: 1779006 | E7: 1779006 | F7: 1779006 | G7: 1779006 | H7: 1779006
A8: Other current assets | B8: 3208021 | C8: 2780247 | D8: 3516640 | E8: ='Other Items'!E16 -> 3969906.7 | F8: ='Other Items'!F16 -> 4423113.6 | G8: ='Other Items'!G16 -> 4928058.9 | H8: ='Other Items'!H16 -> 5490649.1
A9: Total current assets | B9: =SUM(B6:B8) -> 9266473 | C9: =SUM(C6:C8) -> 9918133 | D9: =SUM(D6:D8) -> 13100379 | E9: =SUM(E6:E8) -> 18475983 | F9: =SUM(F6:F8) -> 26046085 | G9: =SUM(G6:G8) -> 34556207 | H9: =SUM(H6:H8) -> 42538806
A10: Content assets, net | B10: 32736713 | C10: 31658056 | D10: 32452462 | E10: =Schedules!E17 -> 33259261 | F10: =Schedules!F17 -> 33811979 | G10: =Schedules!G17 -> 34190632 | H10: =Schedules!H17 -> 34450037
A11: Property and equipment, net | B11: 1398257 | C11: 1491444 | D11: 1593756 | E11: =Schedules!E7 -> 1688154.3 | F11: =Schedules!F7 -> 1793918.7 | G11: =Schedules!G7 -> 1907807.4 | H11: =Schedules!H7 -> 2027657.2
A12: Other non-current assets | B12: 5193325 | C12: 5664359 | D12: 6483777 | E12: 6483777 | F12: 6483777 | G12: 6483777 | H12: 6483777
A13: Total assets | B13: =SUM(B9:B12) -> 48594768 | C13: =SUM(C9:C12) -> 48731992 | D13: =SUM(D9:D12) -> 53630374 | E13: =SUM(E9:E12) -> 59907176 | F13: =SUM(F9:F12) -> 68135760 | G13: =ROUND(SUM(G9:G12),3) -> 77138424 | H13: =ROUND(SUM(H9:H12),3) -> 85500278
A15: Liabilities and Stockholders' Equity
A16: Current liabilities:
A17: Current content liabilities | B17: 4480150 | C17: 4466470 | D17: 4393681 | E17: 4393681 | F17: 4393681 | G17: 4393681 | H17: 4393681
A18: Accounts payable | B18: 671513 | C18: 747412 | D18: 899909 | E18: ='Other Items'!E19 -> 966630.61 | F18: ='Other Items'!F19 -> 1076981.7 | G18: ='Other Items'!G19 -> 1199930.6 | H18: ='Other Items'!H19 -> 1336915.4
A19: Accrued expenses and other liabilities | B19: 1514650 | C19: 1803960 | D19: 2156544 | E19: ='Other Items'!E22 -> 2269654.9 | F19: ='Other Items'!F22 -> 2528760.1 | G19: ='Other Items'!G22 -> 2817444.9 | H19: ='Other Items'!H22 -> 3139086.1
A20: Deferred revenue | B20: 1264661 | C20: 1442969 | D20: 1520813 | E20: ='Other Items'!E25 -> 1763973.3 | F20: ='Other Items'!F25 -> 1965349.6 | G20: ='Other Items'!G25 -> 2189715.1 | H20: ='Other Items'!H25 -> 2439694.2
A21: Short-term debt | B21: - | C21: 399844 | D21: 1784453 | E21: 1784453 | F21: 1784453 | G21: 1784453 | H21: 1784453
A22: Total current liabilities | B22: =SUM(B17:B21) -> 7930974 | C22: =SUM(C17:C21) -> 8860655 | D22: =SUM(D17:D21) -> 10755400 | E22: =SUM(E17:E21) -> 11178393 | F22: =SUM(F17:F21) -> 11749225 | G22: =SUM(G17:G21) -> 12385225 | H22: =SUM(H17:H21) -> 13093830
A23: Non-current content liabilities | B23: 3081277 | C23: 2578173 | D23: 1780806 | E23: 1780806 | F23: 1780806 | G23: 1780806 | H23: 1780806
A24: Long-term debt | B24: 14353076 | C24: 14143417 | D24: 13798351 | E24: =Schedules!E25 -> 12011351 | F24: =Schedules!F25 -> 11011351 | G24: =Schedules!G25 -> 9577351 | H24: =Schedules!H25 -> 6077351
A25: Other non-current liabilities | B25: 2452040 | C25: 2561434 | D25: 2552250 | E25: 2552250 | F25: 2552250 | G25: 2552250 | H25: 2552250
A26: Total liabilities | B26: =SUM(B22:B25) -> 27817367 | C26: =SUM(C22:C25) -> 28143679 | D26: =SUM(D22:D25) -> 28886807 | E26: =SUM(E22:E25) -> 27522800 | F26: =SUM(F22:F25) -> 27093632 | G26: =SUM(G22:G25) -> 26295632 | H26: =SUM(H22:H25) -> 23504237
A27: Stockholders' equity:
A28: Common stock | B28: 4637601 | C28: 5145172 | D28: 6252126 | E28: 6252126 | F28: 6252126 | G28: 6252126 | H28: 6252126
A29: Treasury stock | B29: -824190 | C29: -6922200 | D29: -13171638 | E29: -13171638 | F29: -13171638 | G29: -13171638 | H29: -13171638
A30: Accumulated other comprehensive income (loss) | B30: -217306 | C30: -223945 | D30: 362162 | E30: 362162 | F30: 362162 | G30: 362162 | H30: 362162
A31: Retained earnings | B31: 17181296 | C31: 22589286 | D31: 31300917 | E31: =D31+'P&L'!E21 -> 38941726 | F31: =E31+'P&L'!F21 -> 47599478 | G31: =F31+'P&L'!G21 -> 57400142 | H31: =G31+'P&L'!H21 -> 68553391
A32: Total stockholders' equity | B32: =SUM(B28:B31) -> 20777401 | C32: =SUM(C28:C31) -> 20588313 | D32: =SUM(D28:D31) -> 24743567 | E32: =SUM(E28:E31) -> 32384376 | F32: =SUM(F28:F31) -> 41042128 | G32: =SUM(G28:G31) -> 50842792 | H32: =SUM(H28:H31) -> 61996041
A33: Total liabilities and stockholders' equity | B33: =B26+B32 -> 48594768 | C33: =C26+C32 -> 48731992 | D33: =D26+D32 -> 53630374 | E33: =E26+E32 -> 59907176 | F33: =F26+F32 -> 68135760 | G33: =ROUND(G26+G32,3) -> 77138424 | H33: =ROUND(H26+H32,3) -> 85500278
A36: Check | B36: =B33=B13 -> TRUE | C36: =C33=C13 -> TRUE | D36: =D33=D13 -> TRUE | E36: =E33=E13 -> TRUE | F36: =F33=F13 -> TRUE | G36: =G33=G13 -> TRUE | H36: =H33=H13 -> TRUE

Sheet Cashflow Statement
A1: Cash Flow
A3: (in thousands) | B3: 2022 | C3: 2023 | D3: 2024 | E3: 2025 | F3: 2026 | G3: 2027 | H3: 2028
A4: EBIT | E4: ='P&L'!E15 -> 9529298.9 | F4: ='P&L'!F15 -> 10666988 | G4: ='P&L'!G15 -> 11930017 | H4: ='P&L'!H15 -> 13334143
A5: Operating Taxes | E5: =E4*E6 -> -1371728.1 | F5: =F4*F6 -> -1535496.7 | G5: =G4*G6 -> -1717307.7 | H5: =H4*H6 -> -1919429.6
A6: Tax Rate % | E6: ='P&L'!E20 -> -0.14394848 | F6: ='P&L'!F20 -> -0.14394848 | G6: ='P&L'!G20 -> -0.14394848 | H6: ='P&L'!H20 -> -0.14394848
A7: NOPAT | E7: =E4+E5 -> 8157570.9 | F7: =F4+F5 -> 9131491.4 | G7: =G4+G5 -> 10212709 | H7: =H4+H5 -> 11414714
A8: add Amortization | E8: =Schedules!E16 -> 15289124 | F8: =Schedules!F16 -> 15543205 | G8: =Schedules!G16 -> 15717270 | H8: =Schedules!H16 -> 15836518
A9: add Depreciation | E9: =Schedules!E6 -> 336827.71 | F9: =Schedules!F6 -> 325461.55 | G9: =Schedules!G6 -> 317337.34 | H9: =Schedules!H6 -> 311376.15
A10: Gross Cash Flow | E10: =E7+E8+E9 -> 23783522 | F10: =F7+F8+F9 -> 25000158 | G10: =G7+G8+G9 -> 26247317 | H10: =H7+H8+H9 -> 27562607
A11: Account Payables | E11: ='Other Items'!E19-'Other Items'!D19 -> 66721.61 | F11: ='Other Items'!F19-'Other Items'!E19 -> 110351.13 | G11: ='Other Items'!G19-'Other Items'!F19 -> 122948.88 | H11: ='Other Items'!H19-'Other Items'!G19 -> 136984.8
A12: Deferred Revenue | E12: ='Other Items'!E25-'Other Items'!D25 -> 243160.32 | F12: ='Other Items'!F25-'Other Items'!E25 -> 201376.25 | G12: ='Other Items'!G25-'Other Items'!F25 -> 224365.48 | H12: ='Other Items'!H25-'Other Items'!G25 -> 249979.18
A13: Current content liabilites | E13: 0 | F13: 0 | G13: 0 | H13: 0
A14: Accrued expenses and other liabilities | E14: ='Other Items'!E22-'Other Items'!D22 -> 113110.95 | F14: ='Other Items'!F22-'Other Items'!E22 -> 259105.17 | G14: ='Other Items'!G22-'Other Items'!F22 -> 288684.77 | H14: ='Other Items'!H22-'Other Items'!G22 -> 321641.2
A15: Other current assets | E15: =-('Other Items'!E16-'Other Items'!D16) -> -453266.68 | F15: =-('Other Items'!F16-'Other Items'!E16) -> -453206.93 | G15: =-('Other Items'!G16-'Other Items'!F16) -> -504945.3 | H15: =-('Other Items'!H16-'Other Items'!G16) -> -562590.16
A16: Investments in Working Capital | E16: =SUM(E11:E15) -> -30273.802 | F16: =SUM(F11:F15) -> 117625.62 | G16: =SUM(G11:G15) -> 131053.84 | H16: =SUM(H11:H15) -> 146015.02
A17: Content Assets | E17: =Schedules!E15 -> 16095923 | F17: =Schedules!F15 -> 16095923 | G17: =Schedules!G15 -> 16095923 | H17: =Schedules!H15 -> 16095923
A18: PP&E | E18: =Schedules!E5 -> 431226 | F18: =Schedules!F5 -> 431226 | G18: =Schedules!G5 -> 431226 | H18: =Schedules!H5 -> 431226
A19: Capex: | E19: =-SUM(E17:E18) -> -16527149 | F19: =-SUM(F17:F18) -> -16527149 | G19: =-SUM(G17:G18) -> -16527149 | H19: =-SUM(H17:H18) -> -16527149
A20: Extraordinary Items
A21: UFCF | E21: =E19+E16+E10 -> 7226099.3 | F21: =F19+F16+F10 -> 8590634.8 | G21: =G19+G16+G10 -> 9851221.5 | H21: =H19+H16+H10 -> 11181473
A22: Debt taken (Repaid) | E22: =Schedules!E24 -> -1787000 | F22: =Schedules!F24 -> -1000000 | G22: =Schedules!G24 -> -1434000 | H22: =Schedules!H24 -> -3500000
A23: Interest Expense | E23: =Schedules!E27 -> -603657.86 | F23: =Schedules!F27 -> -553400.57 | G23: =Schedules!G27 -> -481331.63 | H23: =Schedules!H27 -> -305431.14
A24: Diff b/w Operating Taxes & Actual Taxes | E24: ='P&L'!E19-'Cashflow Statement'!E5 -> 86895.628 | F24: ='P&L'!F19-'Cashflow Statement'!F5 -> 79661.169 | G24: ='P&L'!G19-'Cashflow Statement'!G5 -> 69286.954 | H24: ='P&L'!H19-'Cashflow Statement'!H5 -> 43966.347
A25: Net Cash Flow | E25: =SUM(E21:E24) -> 4922337.1 | F25: =SUM(F21:F24) -> 7116895.4 | G25: =SUM(G21:G24) -> 8005176.8 | H25: =SUM(H21:H24) -> 7420008.7

Sheet WACC
A1: WACC
B3: Risk free Rate/ Perpetutity Growth rate (g) | C3: 0.0415 | J3: Cost of Equity = RiskfreeRate*beta + Market Risk Premium
B4: Market Risk Premium | C4: 0.049
B5: Beta | C5: 1.05
B7: (in thousands) | C7: Amount | E7: Sensitivity Analysis
B9: Cost of Equity | C9: =C3*C5+C4 -> 0.092575 | E9: Intrinsic Value/Share | G9: Growth Rate
B10: Cost Debt | C10: 0.054 | F10: =DCF!B23 -> 510.67724 | G10: 0.0375 | H10: 0.0415 | I10: 0.0475
E11: WACC | F11: 0.085 | G11: 516.73967 | H11: 553.97877 | I11: 624.73307
B12: Equity | C12: ='Balance Sheet'!H32 -> 61996041 | F12: 0.0891 | G12: 480.00069 | H12: 510.97569 | I12: 568.60706
B13: Debt | C13: ='Balance Sheet'!H24 -> 6077351 | F13: 0.095 | G13: 436.34174 | H13: 460.6754 | I13: 504.86019
B15: Equity/(Equity+Debt) | C15: =C12/(C12+C13) -> 0.91072355
B16: Debt/(Equity+Debt) | C16: =C13/(C12+C13) -> 0.089276453
B18: WACC | C18: =C9*C15+C10*C16 -> 0.089131161

Sheet DCF
A1: DCF Analysis
A3: (in thousands) | B3: 2025 | C3: 2026 | D3: 2027 | E3: 2028
A4: UFCF | B4: ='Cashflow Statement'!E21 -> 7226099.3 | C4: ='Cashflow Statement'!F21 -> 8590634.8 | D4: ='Cashflow Statement'!G21 -> 9851221.5 | E4: ='Cashflow Statement'!H21 -> 11181473
A5: Discounting Factor | B5: =1/(1+WACC!$C$18)^DCF!B6 -> 0.91816306 | C5: =1/(1+WACC!$C$18)^DCF!C6 -> 0.84302341 | D5: =1/(1+WACC!$C$18)^DCF!D6 -> 0.77403295 | E5: =1/(1+WACC!$C$18)^DCF!E6 -> 0.71068846
A6: No of Years | B6: 1 | C6: 2 | D6: 3 | E6: 4
A8: PV of UFCF | B8: =B4*B5 -> 6634737.5 | C8: =C4*C5 -> 7242106.2 | D8: =D4*D5 -> 7625170 | E8: =E4*E5 -> 7946544.2
A10: Sum of PV | B10: =SUM(B8:E8) -> 29448558
A12: Terminal Value | B12: =E4*(1+WACC!C3)/(WACC!C18-WACC!C3) -> 2.444934e+08
A13: PV of Terminal value | B13: =B12*E5 -> 1.7375864e+08
A16: Enterprise Value | B16: =B13+B10 -> 2.032072e+08
A17: Debt | B17: ='Balance Sheet'!H24 -> 6077351
A18: Cash | B18: ='Balance Sheet'!H6 -> 35269151
A19: Equity Value / Intrinsic Value | B19: =B16+B18-B17 -> 2.32399e+08
A21: Netflix Diluted Outstanding Share on MAR 2024 | B21: 455080
A23: Intrinsic Value per Share | B23: =B19/B21 -> 510.67724
